Zolenmeyer.py
setup.py
Zolenmeyer.egg-info/PKG-INFO
Zolenmeyer.egg-info/SOURCES.txt
Zolenmeyer.egg-info/dependency_links.txt
Zolenmeyer.egg-info/top_level.txt