Metadata-Version: 1.0
Name: Zolenmeyer
Version: 0.1
Summary: Stupid personally customized Flask
Home-page: https://github.com/zorceta/Zolenmeyer
Author: Zorceta Moshak
Author-email: zorceta@gmail.com
License: BSD
Platform: UNKNOWN
